[
    {
        "metric": {
            "__name__": "go_memstats_sys_bytes",
            "group": "production",
            "instance": "node_exporter:9100",
            "job": "node"
        },
        "values": [
            [
                1739745133,
                "15045896"
            ],
            [
                1739745134,
                "15045896"
            ],
            [
                1739745135,
                "15045896"
            ],
            [
                1739745136,
                "15045896"
            ],
            [
                1739745137,
                "15045896"
            ],
            [
                1739745138,
                "15045896"
            ],
            [
                1739745139,
                "15045896"
            ],
            [
                1739745140,
                "15045896"
            ],
            [
                1739745141,
                "15045896"
            ],
            [
                1739745142,
                "15045896"
            ],
            [
                1739745143,
                "15045896"
            ],
            [
                1739745144,
                "15045896"
            ],
            [
                1739745145,
                "15045896"
            ],
            [
                1739745146,
                "15045896"
            ],
            [
                1739745147,
                "15045896"
            ],
            [
                1739745148,
                "15045896"
            ],
            [
                1739745149,
                "15045896"
            ],
            [
                1739745150,
                "15045896"
            ],
            [
                1739745151,
                "15045896"
            ],
            [
                1739745152,
                "15045896"
            ],
            [
                1739745153,
                "15045896"
            ],
            [
                1739745154,
                "15045896"
            ]
        ]
    },
    {
        "metric": {
            "__name__": "go_memstats_sys_bytes",
            "instance": "cadvisor:8080",
            "job": "cadvisor"
        },
        "values": [
            [
                1739745133,
                "64705800"
            ],
            [
                1739745134,
                "64705800"
            ],
            [
                1739745135,
                "64705800"
            ],
            [
                1739745136,
                "64705800"
            ],
            [
                1739745137,
                "64705800"
            ],
            [
                1739745138,
                "64705800"
            ],
            [
                1739745139,
                "64705800"
            ],
            [
                1739745140,
                "64705800"
            ],
            [
                1739745141,
                "64705800"
            ],
            [
                1739745142,
                "64705800"
            ],
            [
                1739745143,
                "64705800"
            ],
            [
                1739745144,
                "64705800"
            ],
            [
                1739745145,
                "64705800"
            ],
            [
                1739745146,
                "64705800"
            ],
            [
                1739745147,
                "64705800"
            ],
            [
                1739745148,
                "64705800"
            ],
            [
                1739745149,
                "64705800"
            ],
            [
                1739745150,
                "64705800"
            ],
            [
                1739745151,
                "64705800"
            ],
            [
                1739745152,
                "64705800"
            ],
            [
                1739745153,
                "64705800"
            ],
            [
                1739745154,
                "64705800"
            ]
        ]
    }
]