[
    {
        "metric": {
            "__name__": "go_goroutines",
            "group": "production",
            "instance": "node_exporter:9100",
            "job": "node"
        },
        "values": [
            [
                1739743610,
                "7"
            ],
            [
                1739743611,
                "7"
            ],
            [
                1739743612,
                "7"
            ],
            [
                1739743613,
                "7"
            ],
            [
                1739743614,
                "7"
            ],
            [
                1739743615,
                "7"
            ],
            [
                1739743616,
                "7"
            ],
            [
                1739743617,
                "7"
            ],
            [
                1739743618,
                "7"
            ],
            [
                1739743619,
                "7"
            ],
            [
                1739743620,
                "7"
            ],
            [
                1739743621,
                "7"
            ],
            [
                1739743622,
                "7"
            ],
            [
                1739743623,
                "7"
            ],
            [
                1739743624,
                "7"
            ],
            [
                1739743625,
                "7"
            ],
            [
                1739743626,
                "7"
            ],
            [
                1739743627,
                "7"
            ],
            [
                1739743628,
                "7"
            ],
            [
                1739743629,
                "7"
            ],
            [
                1739743630,
                "7"
            ],
            [
                1739743631,
                "7"
            ],
            [
                1739743632,
                "7"
            ],
            [
                1739743633,
                "7"
            ],
            [
                1739743634,
                "7"
            ],
            [
                1739743635,
                "7"
            ],
            [
                1739743636,
                "7"
            ],
            [
                1739743637,
                "7"
            ],
            [
                1739743638,
                "7"
            ],
            [
                1739743639,
                "7"
            ],
            [
                1739743640,
                "7"
            ],
            [
                1739743641,
                "8"
            ],
            [
                1739743642,
                "7"
            ],
            [
                1739743643,
                "7"
            ],
            [
                1739743644,
                "7"
            ],
            [
                1739743645,
                "7"
            ],
            [
                1739743646,
                "7"
            ],
            [
                1739743647,
                "7"
            ],
            [
                1739743648,
                "7"
            ],
            [
                1739743649,
                "7"
            ],
            [
                1739743650,
                "7"
            ],
            [
                1739743651,
                "7"
            ],
            [
                1739743652,
                "7"
            ],
            [
                1739743653,
                "7"
            ],
            [
                1739743654,
                "7"
            ],
            [
                1739743655,
                "7"
            ],
            [
                1739743656,
                "7"
            ],
            [
                1739743657,
                "7"
            ],
            [
                1739743658,
                "7"
            ],
            [
                1739743659,
                "7"
            ],
            [
                1739743660,
                "7"
            ],
            [
                1739743661,
                "7"
            ],
            [
                1739743662,
                "7"
            ],
            [
                1739743663,
                "7"
            ],
            [
                1739743664,
                "7"
            ],
            [
                1739743665,
                "7"
            ],
            [
                1739743666,
                "7"
            ],
            [
                1739743667,
                "7"
            ],
            [
                1739743668,
                "7"
            ],
            [
                1739743669,
                "7"
            ],
            [
                1739743670,
                "7"
            ],
            [
                1739743671,
                "7"
            ],
            [
                1739743672,
                "7"
            ],
            [
                1739743673,
                "7"
            ],
            [
                1739743674,
                "7"
            ],
            [
                1739743675,
                "7"
            ],
            [
                1739743676,
                "7"
            ],
            [
                1739743677,
                "7"
            ],
            [
                1739743678,
                "7"
            ],
            [
                1739743679,
                "7"
            ],
            [
                1739743680,
                "7"
            ],
            [
                1739743681,
                "7"
            ],
            [
                1739743682,
                "7"
            ],
            [
                1739743683,
                "7"
            ],
            [
                1739743684,
                "7"
            ],
            [
                1739743685,
                "7"
            ],
            [
                1739743686,
                "7"
            ],
            [
                1739743687,
                "7"
            ],
            [
                1739743688,
                "7"
            ],
            [
                1739743689,
                "7"
            ],
            [
                1739743690,
                "7"
            ],
            [
                1739743691,
                "7"
            ],
            [
                1739743692,
                "7"
            ],
            [
                1739743693,
                "7"
            ],
            [
                1739743694,
                "7"
            ],
            [
                1739743695,
                "7"
            ],
            [
                1739743696,
                "7"
            ],
            [
                1739743697,
                "7"
            ],
            [
                1739743698,
                "7"
            ],
            [
                1739743699,
                "7"
            ],
            [
                1739743700,
                "7"
            ],
            [
                1739743701,
                "7"
            ],
            [
                1739743702,
                "7"
            ],
            [
                1739743703,
                "7"
            ],
            [
                1739743704,
                "7"
            ],
            [
                1739743705,
                "7"
            ],
            [
                1739743706,
                "7"
            ],
            [
                1739743707,
                "7"
            ],
            [
                1739743708,
                "7"
            ],
            [
                1739743709,
                "7"
            ],
            [
                1739743710,
                "7"
            ],
            [
                1739743711,
                "7"
            ],
            [
                1739743712,
                "7"
            ],
            [
                1739743713,
                "7"
            ],
            [
                1739743714,
                "7"
            ],
            [
                1739743715,
                "7"
            ],
            [
                1739743716,
                "7"
            ],
            [
                1739743717,
                "7"
            ],
            [
                1739743718,
                "7"
            ],
            [
                1739743719,
                "7"
            ],
            [
                1739743720,
                "7"
            ],
            [
                1739743721,
                "7"
            ],
            [
                1739743722,
                "7"
            ],
            [
                1739743723,
                "7"
            ],
            [
                1739743724,
                "7"
            ],
            [
                1739743725,
                "7"
            ],
            [
                1739743726,
                "7"
            ],
            [
                1739743727,
                "7"
            ],
            [
                1739743728,
                "7"
            ],
            [
                1739743729,
                "7"
            ],
            [
                1739743730,
                "7"
            ],
            [
                1739743731,
                "7"
            ],
            [
                1739743732,
                "7"
            ],
            [
                1739743733,
                "7"
            ],
            [
                1739743734,
                "7"
            ],
            [
                1739743735,
                "7"
            ],
            [
                1739743736,
                "7"
            ],
            [
                1739743737,
                "7"
            ],
            [
                1739743738,
                "7"
            ],
            [
                1739743739,
                "7"
            ],
            [
                1739743740,
                "7"
            ],
            [
                1739743741,
                "7"
            ],
            [
                1739743742,
                "7"
            ],
            [
                1739743743,
                "7"
            ],
            [
                1739743744,
                "7"
            ],
            [
                1739743745,
                "7"
            ],
            [
                1739743746,
                "7"
            ],
            [
                1739743747,
                "7"
            ],
            [
                1739743748,
                "7"
            ],
            [
                1739743749,
                "7"
            ],
            [
                1739743750,
                "7"
            ],
            [
                1739743751,
                "7"
            ],
            [
                1739743752,
                "7"
            ],
            [
                1739743753,
                "7"
            ],
            [
                1739743754,
                "7"
            ],
            [
                1739743755,
                "7"
            ],
            [
                1739743756,
                "7"
            ],
            [
                1739743757,
                "7"
            ],
            [
                1739743758,
                "7"
            ],
            [
                1739743759,
                "7"
            ],
            [
                1739743760,
                "7"
            ],
            [
                1739743761,
                "7"
            ],
            [
                1739743762,
                "7"
            ],
            [
                1739743763,
                "7"
            ],
            [
                1739743764,
                "7"
            ],
            [
                1739743765,
                "7"
            ],
            [
                1739743766,
                "7"
            ],
            [
                1739743767,
                "7"
            ],
            [
                1739743768,
                "7"
            ],
            [
                1739743769,
                "7"
            ],
            [
                1739743770,
                "7"
            ],
            [
                1739743771,
                "7"
            ],
            [
                1739743772,
                "7"
            ],
            [
                1739743773,
                "7"
            ],
            [
                1739743774,
                "7"
            ],
            [
                1739743775,
                "7"
            ],
            [
                1739743776,
                "7"
            ],
            [
                1739743777,
                "7"
            ],
            [
                1739743778,
                "7"
            ],
            [
                1739743779,
                "7"
            ],
            [
                1739743780,
                "7"
            ],
            [
                1739743781,
                "7"
            ],
            [
                1739743782,
                "7"
            ],
            [
                1739743783,
                "7"
            ]
        ]
    },
    {
        "metric": {
            "__name__": "go_goroutines",
            "instance": "cadvisor:8080",
            "job": "cadvisor"
        },
        "values": [
            [
                1739743610,
                "87"
            ],
            [
                1739743611,
                "87"
            ],
            [
                1739743612,
                "87"
            ],
            [
                1739743613,
                "85"
            ],
            [
                1739743614,
                "85"
            ],
            [
                1739743615,
                "85"
            ],
            [
                1739743616,
                "85"
            ],
            [
                1739743617,
                "85"
            ],
            [
                1739743618,
                "86"
            ],
            [
                1739743619,
                "86"
            ],
            [
                1739743620,
                "87"
            ],
            [
                1739743621,
                "85"
            ],
            [
                1739743622,
                "85"
            ],
            [
                1739743623,
                "86"
            ],
            [
                1739743624,
                "87"
            ],
            [
                1739743625,
                "86"
            ],
            [
                1739743626,
                "87"
            ],
            [
                1739743627,
                "85"
            ],
            [
                1739743628,
                "86"
            ],
            [
                1739743629,
                "85"
            ],
            [
                1739743630,
                "85"
            ],
            [
                1739743631,
                "86"
            ],
            [
                1739743632,
                "85"
            ],
            [
                1739743633,
                "86"
            ],
            [
                1739743634,
                "86"
            ],
            [
                1739743635,
                "87"
            ],
            [
                1739743636,
                "87"
            ],
            [
                1739743637,
                "85"
            ],
            [
                1739743638,
                "85"
            ],
            [
                1739743639,
                "86"
            ],
            [
                1739743640,
                "87"
            ],
            [
                1739743641,
                "85"
            ],
            [
                1739743642,
                "85"
            ],
            [
                1739743643,
                "87"
            ],
            [
                1739743644,
                "86"
            ],
            [
                1739743645,
                "86"
            ],
            [
                1739743646,
                "85"
            ],
            [
                1739743647,
                "86"
            ],
            [
                1739743648,
                "86"
            ],
            [
                1739743649,
                "85"
            ],
            [
                1739743650,
                "86"
            ],
            [
                1739743651,
                "86"
            ],
            [
                1739743652,
                "85"
            ],
            [
                1739743653,
                "86"
            ],
            [
                1739743654,
                "87"
            ],
            [
                1739743655,
                "86"
            ],
            [
                1739743656,
                "86"
            ],
            [
                1739743657,
                "85"
            ],
            [
                1739743658,
                "87"
            ],
            [
                1739743659,
                "87"
            ],
            [
                1739743660,
                "85"
            ],
            [
                1739743661,
                "86"
            ],
            [
                1739743662,
                "85"
            ],
            [
                1739743663,
                "86"
            ],
            [
                1739743664,
                "87"
            ],
            [
                1739743665,
                "87"
            ],
            [
                1739743666,
                "87"
            ],
            [
                1739743667,
                "86"
            ],
            [
                1739743668,
                "86"
            ],
            [
                1739743669,
                "87"
            ],
            [
                1739743670,
                "86"
            ],
            [
                1739743671,
                "86"
            ],
            [
                1739743672,
                "85"
            ],
            [
                1739743673,
                "86"
            ],
            [
                1739743674,
                "85"
            ],
            [
                1739743675,
                "87"
            ],
            [
                1739743676,
                "85"
            ],
            [
                1739743677,
                "85"
            ],
            [
                1739743678,
                "87"
            ],
            [
                1739743679,
                "86"
            ],
            [
                1739743680,
                "85"
            ],
            [
                1739743681,
                "87"
            ],
            [
                1739743682,
                "85"
            ],
            [
                1739743683,
                "86"
            ],
            [
                1739743684,
                "87"
            ],
            [
                1739743685,
                "85"
            ],
            [
                1739743686,
                "85"
            ],
            [
                1739743687,
                "87"
            ],
            [
                1739743688,
                "87"
            ],
            [
                1739743689,
                "86"
            ],
            [
                1739743690,
                "86"
            ],
            [
                1739743691,
                "87"
            ],
            [
                1739743692,
                "85"
            ],
            [
                1739743693,
                "85"
            ],
            [
                1739743694,
                "86"
            ],
            [
                1739743695,
                "85"
            ],
            [
                1739743696,
                "85"
            ],
            [
                1739743697,
                "86"
            ],
            [
                1739743698,
                "85"
            ],
            [
                1739743699,
                "87"
            ],
            [
                1739743700,
                "85"
            ],
            [
                1739743701,
                "87"
            ],
            [
                1739743702,
                "86"
            ],
            [
                1739743703,
                "86"
            ],
            [
                1739743704,
                "85"
            ],
            [
                1739743705,
                "86"
            ],
            [
                1739743706,
                "85"
            ],
            [
                1739743707,
                "86"
            ],
            [
                1739743708,
                "86"
            ],
            [
                1739743709,
                "85"
            ],
            [
                1739743710,
                "86"
            ],
            [
                1739743711,
                "87"
            ],
            [
                1739743712,
                "85"
            ],
            [
                1739743713,
                "87"
            ],
            [
                1739743714,
                "86"
            ],
            [
                1739743715,
                "86"
            ],
            [
                1739743716,
                "85"
            ],
            [
                1739743717,
                "86"
            ],
            [
                1739743718,
                "85"
            ],
            [
                1739743719,
                "87"
            ],
            [
                1739743720,
                "85"
            ],
            [
                1739743721,
                "87"
            ],
            [
                1739743722,
                "86"
            ],
            [
                1739743723,
                "85"
            ],
            [
                1739743724,
                "86"
            ],
            [
                1739743725,
                "85"
            ],
            [
                1739743726,
                "86"
            ],
            [
                1739743727,
                "87"
            ],
            [
                1739743728,
                "86"
            ],
            [
                1739743729,
                "86"
            ],
            [
                1739743730,
                "86"
            ],
            [
                1739743731,
                "87"
            ],
            [
                1739743732,
                "86"
            ],
            [
                1739743733,
                "85"
            ],
            [
                1739743734,
                "87"
            ],
            [
                1739743735,
                "87"
            ],
            [
                1739743736,
                "86"
            ],
            [
                1739743737,
                "87"
            ],
            [
                1739743738,
                "85"
            ],
            [
                1739743739,
                "87"
            ],
            [
                1739743740,
                "85"
            ],
            [
                1739743741,
                "86"
            ],
            [
                1739743742,
                "86"
            ],
            [
                1739743743,
                "87"
            ],
            [
                1739743744,
                "85"
            ],
            [
                1739743745,
                "85"
            ],
            [
                1739743746,
                "87"
            ],
            [
                1739743747,
                "87"
            ],
            [
                1739743748,
                "85"
            ],
            [
                1739743749,
                "86"
            ],
            [
                1739743750,
                "86"
            ],
            [
                1739743751,
                "85"
            ],
            [
                1739743752,
                "87"
            ],
            [
                1739743753,
                "85"
            ],
            [
                1739743754,
                "86"
            ],
            [
                1739743755,
                "86"
            ],
            [
                1739743756,
                "85"
            ],
            [
                1739743757,
                "86"
            ],
            [
                1739743758,
                "86"
            ],
            [
                1739743759,
                "87"
            ],
            [
                1739743760,
                "86"
            ],
            [
                1739743761,
                "87"
            ],
            [
                1739743762,
                "87"
            ],
            [
                1739743763,
                "85"
            ],
            [
                1739743764,
                "85"
            ],
            [
                1739743765,
                "85"
            ],
            [
                1739743766,
                "86"
            ],
            [
                1739743767,
                "85"
            ],
            [
                1739743768,
                "86"
            ],
            [
                1739743769,
                "86"
            ],
            [
                1739743770,
                "86"
            ],
            [
                1739743771,
                "86"
            ],
            [
                1739743772,
                "86"
            ],
            [
                1739743773,
                "87"
            ],
            [
                1739743774,
                "86"
            ],
            [
                1739743775,
                "86"
            ],
            [
                1739743776,
                "86"
            ],
            [
                1739743777,
                "85"
            ],
            [
                1739743778,
                "86"
            ],
            [
                1739743779,
                "85"
            ],
            [
                1739743780,
                "86"
            ],
            [
                1739743781,
                "85"
            ],
            [
                1739743782,
                "86"
            ],
            [
                1739743783,
                "85"
            ]
        ]
    }
]